README.rst
sekube.py
setup.py
sekube.egg-info/PKG-INFO
sekube.egg-info/SOURCES.txt
sekube.egg-info/dependency_links.txt
sekube.egg-info/entry_points.txt
sekube.egg-info/requires.txt
sekube.egg-info/top_level.txt