Metadata-Version: 1.0
Name: sekube
Version: 0.1.6
Summary: Incredibly naivé program to read secrets from a kubernettes cluster
Home-page: https://github.com/zinob/sekube/
Author: Simon Albinsson
Author-email: pipmon@zinob.se
License: MIT
Platform: UNKNOWN
